Metadata-Version: 2.1
Name: sortpics
Version: 0.1.0
Summary: Pictures from Google Photos, ICloud, or your Camera... all sorted!
Home-page: https://github.com/mwouts/sortpics
Author: Marc Wouts
Author-email: marc.wouts@gmail.com
License: MIT
Platform: UNKNOWN
Classifier: Development Status :: 5 - Production/Stable
Classifier: License :: OSI Approved :: MIT License
Classifier: Environment :: Console
Classifier: Intended Audience :: Developers
Classifier: Programming Language :: Python :: 3.5
Classifier: Programming Language :: Python :: 3.6
Classifier: Programming Language :: Python :: 3.7
Classifier: Programming Language :: Python :: 3.8
